ii_slide/__init__.py
ii_slide/cli.py
ii_slide/sync_manager.py
ii_slide/backend/__init__.py
ii_slide/backend/app.py
ii_slide/backend/main.py
ii_slide/backend/state_manager.py
ii_slide/frontend/__init__.py
ii_slide/pptist/__init__.py
ii_slide/pptist/models.py
ii_slide/pptist/types.py
ii_slide/skeleton/__init__.py
ii_slide/skeleton/base.py
ii_slide/skeleton/converter.py
ii_slide/skeleton/manager.py
ii_slide/skeleton/slides.py
ii_slide/templates/__init__.py
ii_slide/templates/models.py
ii_slide/templates/registry.py
ii_slide/utils/__init__.py
ii_slide/utils/utils.py
ii_slide/frontend/dist/favicon.ico
ii_slide/frontend/dist/index.html
ii_slide/frontend/dist/logo.png
ii_slide/frontend/dist/assets/AlibabaPuHuiTi-DmhZZWZO.woff2
ii_slide/frontend/dist/assets/CangerXiaowanzi-DMeiPcG1.woff2
ii_slide/frontend/dist/assets/DeYiHei-Cv0cLOfB.woff2
ii_slide/frontend/dist/assets/FangZhengFangSong-i331GLcV.woff2
ii_slide/frontend/dist/assets/FangZhengHeiTi-CxvR-3vx.woff2
ii_slide/frontend/dist/assets/FangZhengKaiTi-Bg4AoH2e.woff2
ii_slide/frontend/dist/assets/FangZhengShuSong-BoLlmUpO.woff2
ii_slide/frontend/dist/assets/FengguangMingrui-ksNOhX5g.woff2
ii_slide/frontend/dist/assets/LXGWWenKai-DZFs0NHN.woff2
ii_slide/frontend/dist/assets/MiSans-AGu9P6z3.woff2
ii_slide/frontend/dist/assets/RuiziZhenyan-BHKInSJR.woff2
ii_slide/frontend/dist/assets/ShetuModernSquare-FPQ-Yk8S.woff2
ii_slide/frontend/dist/assets/SourceHanSans-yquDYLED.woff2
ii_slide/frontend/dist/assets/SourceHanSerif-BepnSM6I.woff2
ii_slide/frontend/dist/assets/SucaiJishiCoolSquare-D6FYeh6_.woff2
ii_slide/frontend/dist/assets/SucaiJishiKangkang-DybiDsGh.woff2
ii_slide/frontend/dist/assets/TuniuRounded-Cg3Uf6es.woff2
ii_slide/frontend/dist/assets/WenDingPLKaiTi-B5NXxUeg.woff2
ii_slide/frontend/dist/assets/YousheTitleBlack-DvsoQD-n.woff2
ii_slide/frontend/dist/assets/ZcoolHappy-Bl-VMWXg.woff2
ii_slide/frontend/dist/assets/ZhuQueFangSong-DEfOC7qi.woff2
ii_slide/frontend/dist/assets/ZizhiQuXiMai-Cm-DfYJC.woff2
ii_slide-0.1.4.dist-info/METADATA
ii_slide-0.1.4.dist-info/WHEEL
ii_slide-0.1.4.dist-info/entry_points.txt
ii_slide-0.1.4.dist-info/RECORD
