Metadata-Version: 2.4
Name: ii-slide
Version: 0.1.4
Summary: AI-powered PowerPoint synchronization backend
Project-URL: Homepage, https://github.com/yourusername/ii-slide
Project-URL: Documentation, https://github.com/yourusername/ii-slide#readme
Project-URL: Repository, https://github.com/yourusername/ii-slide.git
Project-URL: Bug Tracker, https://github.com/yourusername/ii-slide/issues
Author-email: Your Name <your.email@example.com>
License: MIT
Classifier: Development Status :: 3 - Alpha
Classifier: Intended Audience :: Developers
Classifier: License :: OSI Approved :: MIT License
Classifier: Programming Language :: Python :: 3
Classifier: Programming Language :: Python :: 3.8
Classifier: Programming Language :: Python :: 3.9
Classifier: Programming Language :: Python :: 3.10
Classifier: Programming Language :: Python :: 3.11
Classifier: Programming Language :: Python :: 3.12
Classifier: Topic :: Software Development :: Libraries :: Python Modules
Requires-Dist: fastapi>=0.104.1
Requires-Dist: ipdb>=0.13.13
Requires-Dist: pydantic>=2.5.0
Requires-Dist: python-multipart>=0.0.6
Requires-Dist: requests>=2.31.0
Requires-Dist: uvicorn[standard]>=0.24.0
Requires-Dist: watchdog>=3.0.0
Requires-Dist: websockets>=12.0
Provides-Extra: dev
Requires-Dist: black>=23.0; extra == 'dev'
Requires-Dist: flake8>=6.0; extra == 'dev'
Requires-Dist: mypy>=1.0; extra == 'dev'
Requires-Dist: pytest-asyncio>=0.21.0; extra == 'dev'
Requires-Dist: pytest>=7.0; extra == 'dev'
